README.md
setup.py
pybaiduphoto/API.py
pybaiduphoto/Album.py
pybaiduphoto/General.py
pybaiduphoto/Location.py
pybaiduphoto/OnlineItem.py
pybaiduphoto/Person.py
pybaiduphoto/Requests.py
pybaiduphoto/Thing.py
pybaiduphoto/__init__.py
pybaiduphoto/apiObject.py
pybaiduphoto/contribution.py
pybaiduphoto.egg-info/PKG-INFO
pybaiduphoto.egg-info/SOURCES.txt
pybaiduphoto.egg-info/dependency_links.txt
pybaiduphoto.egg-info/requires.txt
pybaiduphoto.egg-info/top_level.txt
pybaiduphoto/cooperation/__init__.py
pybaiduphoto/cooperation/muyangren907_shoot_time.py
pybaiduphoto/test/__init__.py