Metadata-Version: 2.1
Name: pybaiduphoto
Version: 2025.7.14.1637
Summary: A simple API to interact with baidu-photo
Home-page: https://github.com/HengyueLi/baiduphoto
Author: Hengyue Li
Author-email: 305069590@qq.com
Requires-Python: >=3.6
Requires-Dist: requests>=2.22.0
Requires-Dist: rich>=10.16.1
